securevault.py
securevault_pqc-0.1.1.dist-info/METADATA
securevault_pqc-0.1.1.dist-info/WHEEL
securevault_pqc-0.1.1.dist-info/entry_points.txt
securevault_pqc-0.1.1.dist-info/top_level.txt
securevault_pqc-0.1.1.dist-info/RECORD
