Metadata-Version: 2.4
Name: securevault-pqc
Version: 0.1.1
Summary: Post-quantum file encryption using ML-KEM-768 + X25519
Home-page: https://github.com/yourusername/securevault
Author: Megane Alexis
Author-email: your.email@example.com
Project-URL: Bug Tracker, https://github.com/yourusername/securevault/issues
Classifier: Development Status :: 4 - Beta
Classifier: Intended Audience :: Developers
Classifier: Intended Audience :: Information Technology
Classifier: Topic :: Security :: Cryptography
Classifier: License :: OSI Approved :: MIT License
Classifier: Programming Language :: Python :: 3
Classifier: Programming Language :: Python :: 3.9
Classifier: Programming Language :: Python :: 3.10
Classifier: Programming Language :: Python :: 3.11
Classifier: Programming Language :: Python :: 3.12
Classifier: Operating System :: OS Independent
Requires-Python: >=3.9
Requires-Dist: liboqs-python>=0.8.0
Requires-Dist: cryptography>=41.0.0
Requires-Dist: click>=8.1.0
Dynamic: author
Dynamic: author-email
Dynamic: classifier
Dynamic: description
Dynamic: description-content-type
Dynamic: home-page
Dynamic: project-url
Dynamic: requires-dist
Dynamic: requires-python
Dynamic: summary
